breadcrumb/__init__.py
breadcrumb/config.py
breadcrumb/integration.py
breadcrumb/capture/__init__.py
breadcrumb/capture/secret_redactor.py
breadcrumb/cli/__init__.py
breadcrumb/cli/formatters.py
breadcrumb/cli/main.py
breadcrumb/cli/main.py.bak
breadcrumb/cli/commands/__init__.py
breadcrumb/cli/commands/config.py
breadcrumb/cli/commands/exceptions.py
breadcrumb/cli/commands/get.py
breadcrumb/cli/commands/list.py
breadcrumb/cli/commands/performance.py
breadcrumb/cli/commands/query.py
breadcrumb/cli/commands/run.py
breadcrumb/cli/commands/serve_mcp.py
breadcrumb/cli/commands/smart_query.py
breadcrumb/cli/commands/top.py
breadcrumb/instrumentation/README.md
breadcrumb/instrumentation/__init__.py
breadcrumb/instrumentation/call_tracker.py
breadcrumb/instrumentation/pep669_backend.py
breadcrumb/instrumentation/settrace_backend.py
breadcrumb/mcp/__init__.py
breadcrumb/mcp/server.py
breadcrumb/storage/__init__.py
breadcrumb/storage/async_writer.py
breadcrumb/storage/connection.py
breadcrumb/storage/query.py
breadcrumb/storage/retention.py
breadcrumb/storage/schema.sql
breadcrumb/storage/smart_queries.py
breadcrumb/storage/value_truncation.py
breadcrumb/storage/migrations/__init__.py
breadcrumb/storage/migrations/migration_manager.py
breadcrumb/storage/migrations/v1_initial.sql
breadcrumb-0.2.14.dist-info/METADATA
breadcrumb-0.2.14.dist-info/WHEEL
breadcrumb-0.2.14.dist-info/entry_points.txt
breadcrumb-0.2.14.dist-info/licenses/LICENSE
breadcrumb-0.2.14.dist-info/RECORD
