Metadata-Version: 2.4
Name: breadcrumb
Version: 0.2.14
Summary: An automatic, non-intrusive execution tracer for Python for iterative IDE-less debugging and code-flow analysis
Project-URL: Homepage, https://github.com/yourusername/breadcrumb
Project-URL: Repository, https://github.com/yourusername/breadcrumb
Project-URL: Issues, https://github.com/yourusername/breadcrumb/issues
Project-URL: Documentation, https://github.com/yourusername/breadcrumb#readme
Author: Breadcrumb Contributors
License: MIT
License-File: LICENSE
Keywords: ai,claude,debugging,execution-tracer,instrumentation,llm,mcp,observability,profiling,tracing
Classifier: Development Status :: 4 - Beta
Classifier: Intended Audience :: Developers
Classifier: License :: OSI Approved :: MIT License
Classifier: Operating System :: OS Independent
Classifier: Programming Language :: Python :: 3
Classifier: Programming Language :: Python :: 3.10
Classifier: Programming Language :: Python :: 3.11
Classifier: Programming Language :: Python :: 3.12
Classifier: Programming Language :: Python :: 3.13
Classifier: Topic :: Software Development :: Debuggers
Classifier: Topic :: Software Development :: Libraries :: Python Modules
Classifier: Topic :: System :: Monitoring
Classifier: Typing :: Typed
Requires-Python: >=3.10
Requires-Dist: duckdb>=1.4.1
Requires-Dist: fastmcp>=2.12.4
Requires-Dist: mcp>=1.17.0
Requires-Dist: pyyaml>=6.0
Requires-Dist: typer>=0.19.2
Provides-Extra: dev
Requires-Dist: flock-core>=0.5.0b70; extra == 'dev'
Requires-Dist: pytest-asyncio>=0.23.0; extra == 'dev'
Requires-Dist: pytest>=8.4.2; extra == 'dev'
